c2p/__init__.py
c2p/__version__.py
c2p/main.py
c2p-2017.0.1.1505301916.dist-info/DESCRIPTION.rst
c2p-2017.0.1.1505301916.dist-info/METADATA
c2p-2017.0.1.1505301916.dist-info/RECORD
c2p-2017.0.1.1505301916.dist-info/WHEEL
c2p-2017.0.1.1505301916.dist-info/metadata.json
c2p-2017.0.1.1505301916.dist-info/top_level.txt
