Metadata-Version: 2.0
Name: c2p
Version: 2017.0.1.1505301916
Summary: HRL Code to Production on Python Projects
Home-page: https://gitlab.com/hrl-upm-software/c2p-python
Author: Harbor Research Laboratory UPM
Author-email: development@hrl-upm.es
License: MIT
Platform: UNKNOWN
Classifier: License :: OSI Approved :: MIT License
Classifier: Programming Language :: Python
Classifier: Programming Language :: Python :: 3.6
Classifier: Programming Language :: Python :: Implementation :: CPython
Classifier: Programming Language :: Python :: Implementation :: PyPy
Requires-Dist: requests
Requires-Dist: twine
